get_multiline_input_with_editor.py
get_multiline_input_with_editor-0.1.0a3.dist-info/licenses/LICENSE
get_multiline_input_with_editor-0.1.0a3.dist-info/METADATA
get_multiline_input_with_editor-0.1.0a3.dist-info/WHEEL
get_multiline_input_with_editor-0.1.0a3.dist-info/top_level.txt
get_multiline_input_with_editor-0.1.0a3.dist-info/RECORD
