Metadata-Version: 2.4
Name: get-multiline-input-with-editor
Version: 0.1.0a3
Summary: Opens a text editor for multi-line input, returns input as a Unicode string. Just like what Git does.
Author-email: Jifeng Wu <jifengwu2k@gmail.com>
License-Expression: MIT
Project-URL: Homepage, https://github.com/jifengwu2k/get-multiline-input-with-editor
Project-URL: Bug Tracker, https://github.com/jifengwu2k/get-multiline-input-with-editor/issues
Classifier: Programming Language :: Python :: 2
Classifier: Programming Language :: Python :: 3
Classifier: Operating System :: OS Independent
Requires-Python: >=2
License-File: LICENSE
Requires-Dist: get-args-to-launch-editor
Dynamic: license-file
